lcacollect_config/__init__.py
lcacollect_config/config.py
lcacollect_config/connection.py
lcacollect_config/context.py
lcacollect_config/email.py
lcacollect_config/exceptions.py
lcacollect_config/fastapi.py
lcacollect_config/formatting.py
lcacollect_config/graphql/__init__.py
lcacollect_config/graphql/input_filters.py
lcacollect_config/graphql/pagination.py
lcacollect_config/load_db.py
lcacollect_config/permissions.py
lcacollect_config/router.py
lcacollect_config/security.py
lcacollect_config/user.py
lcacollect_config/validate.py
lcacollect_config-1.8.0.dist-info/LICENSE
lcacollect_config-1.8.0.dist-info/METADATA
lcacollect_config-1.8.0.dist-info/WHEEL
lcacollect_config-1.8.0.dist-info/RECORD
