Metadata-Version: 2.1
Name: lcacollect-config
Version: 1.8.0
Summary: This package contains shared config and utils to be used across LCAcollect backends.
Home-page: https://github.com/lcacollect/shared-config-backend
License: Apache-2.0
Author: Christian Kongsgaard
Author-email: chrk@arkitema.com
Requires-Python: >=3.11,<4.0
Classifier: License :: OSI Approved :: Apache Software License
Classifier: Programming Language :: Python :: 3
Classifier: Programming Language :: Python :: 3.11
Classifier: Programming Language :: Python :: 3.12
Provides-Extra: database
Requires-Dist: SQLAlchemy[asyncio] (>=1.4.35) ; extra == "database"
Requires-Dist: aiocache
Requires-Dist: asyncpg (>=0.26.0,<0.27.0) ; extra == "database"
Requires-Dist: azure-identity
Requires-Dist: fastapi-azure-auth (>=4.0.0)
Requires-Dist: msgraph-core
Requires-Dist: pydantic
Requires-Dist: requests
Requires-Dist: sendgrid
Requires-Dist: sqlmodel (>=0.0.8) ; extra == "database"
Requires-Dist: strawberry-graphql[fastapi] (>=0.209.0)
Project-URL: Repository, https://github.com/lcacollect/shared-config-backend
